allot.py
allot-0.2.dist-info/LICENSE
allot-0.2.dist-info/WHEEL
allot-0.2.dist-info/METADATA
allot-0.2.dist-info/RECORD
