Metadata-Version: 2.1
Name: allot
Version: 0.2
Summary: A more fine-grained functools.singledispatch
Home-page: https://github.com/flying-sheep/allot
License: UNKNOWN
Author: Philipp A.
Author-email: flying-sheep@web.de
Requires-Python: >=3.6
Classifier: Intended Audience :: Developers
Classifier: License :: OSI Approved :: GNU General Public License v3 or later (GPLv3+)
Classifier: Programming Language :: Python :: 3
Requires-Dist: get_version
Requires-Dist: pytest; extra == "test"
Requires-Dist: pytest-black; extra == "test"
Requires-Dist: pytest-cov; extra == "test"
Requires-Dist: docutils; extra == "test"
Requires-Dist: pygments; extra == "test"
Provides-Extra: test
